pirateweather/__init__.py
pirateweather/data.py
pirateweather/forecast.py
pirateweatherlib-0.4.0.dist-info/LICENSE
pirateweatherlib-0.4.0.dist-info/METADATA
pirateweatherlib-0.4.0.dist-info/WHEEL
pirateweatherlib-0.4.0.dist-info/RECORD
