Metadata-Version: 2.1
Name: pirateweatherlib
Version: 0.4.0
Summary: A Pirate Weather API wrapper
Home-page: https://github.com/noblecloud/pirateweatherlib
License: MIT
Keywords: pirateweather,pirate-weather,pirate,forecast,home weather,home-weather,weather-station
Author: Lukas Kubis and adapted for Pirate Weather by noblecloud
Requires-Python: >=3.6,<4.0
Classifier: Development Status :: 4 - Beta
Classifier: Intended Audience :: Developers
Classifier: Intended Audience :: Education
Classifier: Intended Audience :: Science/Research
Classifier: License :: OSI Approved :: MIT License
Classifier: Natural Language :: English
Classifier: Operating System :: OS Independent
Classifier: Programming Language :: Python :: 3
Classifier: Programming Language :: Python :: 3.6
Classifier: Programming Language :: Python :: 3.7
Classifier: Programming Language :: Python :: 3.8
Classifier: Programming Language :: Python :: 3.9
Classifier: Programming Language :: Python :: 3.10
Classifier: Programming Language :: Python :: 3.11
Classifier: Programming Language :: Python :: 3.11
Classifier: Topic :: Home Automation
Classifier: Topic :: Scientific/Engineering :: Atmospheric Science
Classifier: Topic :: Software Development :: Libraries
Classifier: Topic :: Software Development :: Libraries :: Python Modules
Classifier: Topic :: Utilities
Provides-Extra: dev
Project-URL: Repository, https://github.com/noblecloud/pirateweatherlib
